{
  "content" : [
    {
      "name": "Customer Services"
    },
    {
      "name": "Finance / Accounting Department"
    },
    {
      "name": "Human Resources / Personnel Department / Staff Department"
    },
    {
      "name": "I.T. (Information Technology)"
    },
    {
      "name": "Logistics"
    },
    {
      "name": "Maintenance"
    },
    {
      "name": "Marketing"
    },
    {
      "name": "Public Relations Team / Public Relations Department"
    },
    {
      "name": "Production Department / Manufacturing Department"
    },
    {
      "name": "Research and Development / Engineering Department"
    },
    {
      "name": "Sales"
    },
    {
      "name": "Shipping Department / Dispatch Department"
    },
    {
      "name": "Technical Support Team"
    }
  ],
  "pageable": {
    "sort": {
      "sorted": false,
      "unsorted": true,
      "empty": true
    },
    "offset": 2,
    "pageNumber": 2,
    "pageSize": 1,
    "paged": true,
    "unpaged": false
  },
  "totalPages": 5,
  "totalElements": 5,
  "last": false,
  "size": 1,
  "number": 2,
  "sort": {
    "sorted": false,
    "unsorted": true,
    "empty": true
  },
  "numberOfElements": 1,
  "first": false,
  "empty": false
}
